icybackup/__init__.py
icybackup/admin.py
icybackup/models.py
icybackup/components/__init__.py
icybackup/components/db.py
icybackup/components/glacier.py
icybackup/management/__init__.py
icybackup/management/commands/__init__.py
icybackup/management/commands/backup.py
icybackup/management/commands/restore.py
icybackup/migrations/0001_initial.py
icybackup/migrations/__init__.py
django_icybackup_jl-0.1.10.dist-info/METADATA
django_icybackup_jl-0.1.10.dist-info/WHEEL
django_icybackup_jl-0.1.10.dist-info/top_level.txt
django_icybackup_jl-0.1.10.dist-info/RECORD
